zen/commands/__init__.py
zen/commands/prs.py
zen/commands/repos.py
zen/main/zen.py
zen_git-0.1.7.dist-info/entry_points.txt
zen_git-0.1.7.dist-info/LICENSE
zen_git-0.1.7.dist-info/WHEEL
zen_git-0.1.7.dist-info/METADATA
zen_git-0.1.7.dist-info/RECORD
